{
    "key": "items/weapon/spear/lance_of_flame",
    "icon": "\ud83c\udf62",
    "name": "Lance of Flame",
    "value": 2335,
    "rarity": "Uncommon",
    "description": "",
    "flavor_text": "",
    "class_tags": [
        "Equipment",
        "Weapon",
        "Spear",
        "Main_Hand"
    ],
    "state_tags": [],
    "count": 1,
    "level_requirement": 46,
    "altering_item_keys": [],
    "item_effects": {
        "permanent": [],
        "on_turn_start": [],
        "on_turn_end": [],
        "on_damaged": [
            {
                "effect_type": "ChanceStatusEffect",
                "effect_value": 1,
                "effect_time": 3,
                "conditions": [],
                "condition_values": [],
                "associated_status_effect": "FixedDmgTick"
            }
        ],
        "on_successful_ability_used": [],
        "on_successful_attack": [],
        "on_attacked": [],
        "on_ability_used_against": []
    },
    "weapon_stats": {
        "min_damage": 17,
        "max_damage": 23,
        "num_targets": 1
    },
    "attr_requirements": {
        "dexterity": 23
    }
}