{
    "key": "items/consumable/potions/potion_of_eternal_life",
    "icon": "\u2697\uFE0F",
    "name": "Potion of Eternal Life",
    "value": 5050,
    "rarity": "Artifact",
    "description": "Can be used while dueling.",
    "flavor_text": "",
    "class_tags": ["Consumable", "Usable_Outside_Duels", "Usable_Within_Duels", "Potion"],
    "state_tags": [],
    "count": 1,
    "consumable_stats": {
        "num_targets": 0,
        "target_own_group": true
    },
    "item_effects": {
        "permanent": [
            {
                "effect_type": "ChanceStatusEffect",
                "effect_value": 1,
                "effect_time": 10,
                "conditions": [],
                "condition_values": [],
                "associated_status_effect": "Undying"
            }
        ]
    }
}