{
    "key": "items/equipment/boots/shoes_of_decay",
    "icon": "\ud83e\udd7e",
    "name": "Shoes of Decay",
    "value": 3460,
    "rarity": "Uncommon",
    "description": "",
    "flavor_text": "",
    "class_tags": [
        "Equipment",
        "Boots"
    ],
    "state_tags": [],
    "count": 1,
    "level_requirement": 66,
    "altering_item_keys": [],
    "item_effects": {
        "permanent": [],
        "on_turn_start": [],
        "on_turn_end": [],
        "on_damaged": [
            {
                "effect_type": "ChanceStatusEffect",
                "effect_value": 0.15,
                "effect_time": 1,
                "conditions": [],
                "condition_values": [],
                "associated_status_effect": "Decaying"
            }
        ],
        "on_successful_ability_used": [],
        "on_successful_attack": [],
        "on_attacked": [],
        "on_ability_used_against": []
    },
    "armor_stats": {
        "armor_amount": 110
    },
    "attr_requirements": {
        "constitution": 39
    }
}